syncthing/__init__.py
syncthing/meta.py
test_syncthing-2.4.2.dist-info/LICENSE
test_syncthing-2.4.2.dist-info/METADATA
test_syncthing-2.4.2.dist-info/WHEEL
test_syncthing-2.4.2.dist-info/top_level.txt
test_syncthing-2.4.2.dist-info/zip-safe
test_syncthing-2.4.2.dist-info/RECORD
